pysoplot/__init__.py
pysoplot/cfg.py
pysoplot/concordia.py
pysoplot/data.py
pysoplot/exceptions.py
pysoplot/isochron.py
pysoplot/misc.py
pysoplot/monte_carlo.py
pysoplot/plotting.py
pysoplot/regression.py
pysoplot/stats.py
pysoplot/transform.py
pysoplot/upb.py
pysoplot/useries.py
pysoplot/wtd_average.py
pysoplot/uxpb/__init__.py
pysoplot/uxpb/corrected.py
pysoplot/uxpb/dqmc.py
pysoplot/uxpb/dqmin.py
pysoplot/uxpb/dqpb.py
pysoplot/uxpb/guillong.py
pysoplot/uxpb/ludwig.py
pysoplot/uxpb/minimise.py
pysoplot/uxpb/wendt_carl.py
pysoplot-0.0.2.dist-info/LICENSE.md
pysoplot-0.0.2.dist-info/METADATA
pysoplot-0.0.2.dist-info/WHEEL
pysoplot-0.0.2.dist-info/top_level.txt
pysoplot-0.0.2.dist-info/RECORD
